{
  "enumData": [
    {
      "Entries": [
        {
          "Name": "None",
          "Value": 0
        },
        {
          "Name": "HideInHierarchy",
          "Value": 1
        },
        {
          "Name": "HideInInspector",
          "Value": 2
        },
        {
          "Name": "DontSaveInEditor",
          "Value": 4
        },
        {
          "Name": "NotEditable",
          "Value": 8
        },
        {
          "Name": "DontSaveInBuild",
          "Value": 16
        },
        {
          "Name": "DontUnloadUnusedAsset",
          "Value": 32
        },
        {
          "Name": "DontSave",
          "Value": 52
        },
        {
          "Name": "HideAndDontSave",
          "Value": 61
        }
      ],
      "Flags": true,
      "id": "contentFlags"
    },
    {
      "Entries": [
        {
          "Name": "Sword",
          "Value": 0
        },
        {
          "Name": "Staff",
          "Value": 1
        },
        {
          "Name": "Shield",
          "Value": 2
        }
      ],
      "Flags": false,
      "id": "WeaponType"
    }
  ],
  "categories": [
    {
      "name": "pcg:CarveHeightmaps",
      "type": "Boolean",
      "displayColor": {
        "r": 0.0,
        "g": 0.0,
        "b": 0.0,
        "a": 0.0
      },
      "defaultContent": {
        "$type": "Achioto.Gamespace_PCG.Runtime.Graph.Serialization.BooleanHGraphAttribute, achioto.gamespace-pcg",
        "Value": false,
        "FeatureVectorLength": 1
      },
      "minValue": "NaN",
      "maxValue": "NaN",
      "id": "pcg:CarveHeightmaps"
    },
    {
      "name": "pcg:epsilon",
      "type": "Float",
      "displayColor": {
        "r": 0.0,
        "g": 0.0,
        "b": 0.0,
        "a": 0.0
      },
      "defaultContent": {
        "$type": "Achioto.Gamespace_PCG.Runtime.Graph.Serialization.FloatHGraphAttribute, achioto.gamespace-pcg",
        "Value": 10.0,
        "FeatureVectorLength": 1
      },
      "minValue": "NaN",
      "maxValue": "NaN",
      "id": "pcg:epsilon"
    },
    {
      "name": "pcg:randomizeRotation",
      "type": "Boolean",
      "displayColor": {
        "r": 0.0,
        "g": 0.0,
        "b": 0.0,
        "a": 0.0
      },
      "defaultContent": {
        "$type": "Achioto.Gamespace_PCG.Runtime.Graph.Serialization.BooleanHGraphAttribute, achioto.gamespace-pcg",
        "Value": true,
        "FeatureVectorLength": 1
      },
      "minValue": "NaN",
      "maxValue": "NaN",
      "id": "pcg:randomizeRotation"
    },
    {
      "name": "pcg:randomizeTilt",
      "type": "Boolean",
      "displayColor": {
        "r": 0.0,
        "g": 0.0,
        "b": 0.0,
        "a": 0.0
      },
      "defaultContent": {
        "$type": "Achioto.Gamespace_PCG.Runtime.Graph.Serialization.BooleanHGraphAttribute, achioto.gamespace-pcg",
        "Value": false,
        "FeatureVectorLength": 1
      },
      "minValue": "NaN",
      "maxValue": "NaN",
      "id": "pcg:randomizeTilt"
    },
    {
      "name": "pcg:maxAssetTiltAngle",
      "type": "Float",
      "displayColor": {
        "r": 0.0,
        "g": 0.0,
        "b": 0.0,
        "a": 0.0
      },
      "defaultContent": {
        "$type": "Achioto.Gamespace_PCG.Runtime.Graph.Serialization.FloatHGraphAttribute, achioto.gamespace-pcg",
        "Value": 0.0,
        "FeatureVectorLength": 1
      },
      "minValue": 0.0,
      "maxValue": 360.0,
      "id": "pcg:maxAssetTiltAngle"
    },
    {
      "name": "pcg:contentFlags",
      "type": "FlagsEnum",
      "displayColor": {
        "r": 0.0,
        "g": 0.0,
        "b": 0.0,
        "a": 0.0
      },
      "defaultContent": {
        "$type": "Achioto.Gamespace_PCG.Runtime.Graph.Serialization.FlagsEnumHGraphAttribute, achioto.gamespace-pcg",
        "Enum": "contentFlags",
        "Value": 0,
        "FeatureVectorLength": 16
      },
      "minValue": "NaN",
      "maxValue": "NaN",
      "id": "pcg:contentFlags"
    },
    {
      "name": "pcg:randomizeScale",
      "type": "Boolean",
      "displayColor": {
        "r": 0.0,
        "g": 0.0,
        "b": 0.0,
        "a": 0.0
      },
      "defaultContent": {
        "$type": "Achioto.Gamespace_PCG.Runtime.Graph.Serialization.BooleanHGraphAttribute, achioto.gamespace-pcg",
        "Value": false,
        "FeatureVectorLength": 1
      },
      "minValue": "NaN",
      "maxValue": "NaN",
      "id": "pcg:randomizeScale"
    },
    {
      "name": "pcg:minScale",
      "type": "Vector3",
      "displayColor": {
        "r": 0.0,
        "g": 0.0,
        "b": 0.0,
        "a": 0.0
      },
      "defaultContent": {
        "$type": "Achioto.Gamespace_PCG.Runtime.Graph.Serialization.Vector3HGraphAttribute, achioto.gamespace-pcg",
        "Vector": {
          "x": 1.0,
          "y": 1.0,
          "z": 1.0
        },
        "FeatureVectorLength": 3
      },
      "minValue": "NaN",
      "maxValue": "NaN",
      "id": "pcg:minScale"
    },
    {
      "name": "pcg:maxScale",
      "type": "Vector3",
      "displayColor": {
        "r": 0.0,
        "g": 0.0,
        "b": 0.0,
        "a": 0.0
      },
      "defaultContent": {
        "$type": "Achioto.Gamespace_PCG.Runtime.Graph.Serialization.Vector3HGraphAttribute, achioto.gamespace-pcg",
        "Vector": {
          "x": 1.0,
          "y": 1.0,
          "z": 1.0
        },
        "FeatureVectorLength": 3
      },
      "minValue": "NaN",
      "maxValue": "NaN",
      "id": "pcg:maxScale"
    },
    {
      "name": "pcg:absolutRotation",
      "type": "Boolean",
      "displayColor": {
        "r": 0.0,
        "g": 0.0,
        "b": 0.0,
        "a": 0.0
      },
      "defaultContent": {
        "$type": "Achioto.Gamespace_PCG.Runtime.Graph.Serialization.BooleanHGraphAttribute, achioto.gamespace-pcg",
        "Value": false,
        "FeatureVectorLength": 1
      },
      "minValue": "NaN",
      "maxValue": "NaN",
      "id": "pcg:absolutRotation"
    },
    {
      "name": "pcg:offset",
      "type": "Vector3",
      "displayColor": {
        "r": 0.0,
        "g": 0.0,
        "b": 0.0,
        "a": 0.0
      },
      "defaultContent": {
        "$type": "Achioto.Gamespace_PCG.Runtime.Graph.Serialization.Vector3HGraphAttribute, achioto.gamespace-pcg",
        "Vector": {
          "x": 0.0,
          "y": 0.0,
          "z": 0.0
        },
        "FeatureVectorLength": 3
      },
      "minValue": "NaN",
      "maxValue": "NaN",
      "id": "pcg:offset"
    },
    {
      "name": "pcg:Difficulty",
      "type": "Float",
      "displayColor": {
        "r": 0.0,
        "g": 0.0,
        "b": 0.0,
        "a": 0.0
      },
      "defaultContent": {
        "$type": "Achioto.Gamespace_PCG.Runtime.Graph.Serialization.FloatHGraphAttribute, achioto.gamespace-pcg",
        "Value": 0.0,
        "FeatureVectorLength": 1
      },
      "minValue": "NaN",
      "maxValue": "NaN",
      "id": "pcg:Difficulty"
    },
    {
      "name": "pcg:wfc:DisallowRoofs",
      "type": "Boolean",
      "displayColor": {
        "r": 0.0,
        "g": 0.0,
        "b": 0.0,
        "a": 0.0
      },
      "defaultContent": {
        "$type": "Achioto.Gamespace_PCG.Runtime.Graph.Serialization.BooleanHGraphAttribute, achioto.gamespace-pcg",
        "Value": false,
        "FeatureVectorLength": 1
      },
      "minValue": "NaN",
      "maxValue": "NaN",
      "id": "pcg:wfc:DisallowRoofs"
    },
    {
      "name": "pcg:wfc:ManyFountains",
      "type": "Boolean",
      "displayColor": {
        "r": 0.0,
        "g": 0.0,
        "b": 0.0,
        "a": 0.0
      },
      "defaultContent": {
        "$type": "Achioto.Gamespace_PCG.Runtime.Graph.Serialization.BooleanHGraphAttribute, achioto.gamespace-pcg",
        "Value": false,
        "FeatureVectorLength": 1
      },
      "minValue": "NaN",
      "maxValue": "NaN",
      "id": "pcg:wfc:ManyFountains"
    },
    {
      "name": "pcg:WeaponType",
      "type": "Enum",
      "displayColor": {
        "r": 0.0,
        "g": 0.0,
        "b": 0.0,
        "a": 0.0
      },
      "defaultContent": {
        "$type": "Achioto.Gamespace_PCG.Runtime.Graph.Serialization.EnumHGraphAttribute, achioto.gamespace-pcg",
        "Enum": "WeaponType",
        "Value": 0,
        "FeatureVectorLength": 16
      },
      "minValue": "NaN",
      "maxValue": "NaN",
      "id": "pcg:WeaponType"
    },
    {
      "name": "Temperature",
      "type": "Float",
      "displayColor": {
        "r": 0.0,
        "g": 0.0,
        "b": 0.0,
        "a": 0.0
      },
      "defaultContent": {
        "$type": "Achioto.Gamespace_PCG.Runtime.Graph.Serialization.FloatHGraphAttribute, achioto.gamespace-pcg",
        "Value": 0.0,
        "FeatureVectorLength": 1
      },
      "minValue": -100.0,
      "maxValue": 100.0,
      "id": "Temperature"
    }
  ],
  "nodes": [
    {
      "name": null,
      "superNode": null,
      "attributes": [
        {
          "category": "Temperature",
          "type": "Float",
          "data": {
            "$type": "Achioto.Gamespace_PCG.Runtime.Graph.Serialization.FloatHGraphAttribute, achioto.gamespace-pcg",
            "Value": -10.0,
            "FeatureVectorLength": 1
          }
        }
      ],
      "relations": [],
      "spaceData": {
        "isAtomic": false,
        "isImplicit": false,
        "nodePosition": {
          "x": 0.0,
          "y": 0.0,
          "z": 0.0
        },
        "nodeRotation": {
          "x": 0.0,
          "y": 0.0,
          "z": 0.0,
          "w": 1.0
        },
        "nodeScale": {
          "x": 1.0,
          "y": 1.0,
          "z": 1.0
        },
        "colliderType": "BoxCollider",
        "center": {
          "x": 0.0,
          "y": 0.0,
          "z": 0.0
        },
        "size": {
          "x": 10.0,
          "y": 10.0,
          "z": 10.0
        },
        "radius": 0.0,
        "height": 0.0,
        "direction": 0
      },
      "id": "Node"
    }
  ],
  "relations": [],
  "rulesGUID": ""
}